labelgui/__init__.py
labelgui/__main__.py
labelgui/check.py
labelgui/config.py
labelgui/helper_gui.py
labelgui/helper_video.py
labelgui/labeling_gui.py
labelgui/labeling_gui_cfg.py
labelgui/select_user.py
bbo_labelgui-0.17.1.dist-info/METADATA
bbo_labelgui-0.17.1.dist-info/WHEEL
bbo_labelgui-0.17.1.dist-info/licenses/LICENSE
bbo_labelgui-0.17.1.dist-info/RECORD
