Metadata-Version: 2.3
Name: bbo-labelgui
Version: 0.17.1
Summary: GUI for guided data labeling
Project-URL: Homepage, https://github.com/bbo-lab/acm-traingui
Author-email: "BBO-lab @ caesar" <kay-michael.voit@mpinb.mpg.de>
License-Expression: LGPL-3.0-or-later
License-File: LICENSE
Classifier: License :: OSI Approved :: GNU Lesser General Public License v2 or later (LGPLv2+)
Classifier: Programming Language :: Python :: 3.10
Requires-Dist: bbo-bbo>=0.1.0
Requires-Dist: bbo-ccvtools
Requires-Dist: bbo-svidreader
Requires-Dist: imageio
Requires-Dist: matplotlib
Requires-Dist: numpy
Requires-Dist: tqdm
